pygameFPS/__init__.py
pygameFPS-1.0.5.dist-info/LICENSE.md
pygameFPS-1.0.5.dist-info/METADATA
pygameFPS-1.0.5.dist-info/WHEEL
pygameFPS-1.0.5.dist-info/top_level.txt
pygameFPS-1.0.5.dist-info/RECORD
