Metadata-Version: 2.1
Name: pygameFPS
Version: 1.0.5
Summary: A package to show your fps in pygame
Author-email: Sheep26 <anEmail@gmail.com>
Project-URL: Homepage, https://github.com/Sheep26/pygameFPS/
Project-URL: Bug Tracker, https://github.com/Sheep26/pygameFPS/issues
Classifier: Programming Language :: Python :: 3
Classifier: License :: OSI Approved :: MIT License
Classifier: Operating System :: OS Independent
Requires-Python: >=3.7
License-File: LICENSE.md
